pyrecswitch/__init__.py
pyrecswitch/constants.py
pyrecswitch/exceptions.py
pyrecswitch/helpers.py
pyrecswitch/interfaces.py
pyrecswitch/messages.py
pyrecswitch/structures.py
pyrecswitch-1.0.2.dist-info/METADATA
pyrecswitch-1.0.2.dist-info/RECORD
pyrecswitch-1.0.2.dist-info/WHEEL
pyrecswitch-1.0.2.dist-info/top_level.txt
