Metadata-Version: 2.1
Name: pyrecswitch
Version: 1.0.2
Summary: A pure-python interface for controlling Ankuoo RecSwitch MS6126
Home-page: https://github.com/marcolertora/pyrecswitch
Author: Marco Lertora
Author-email: marco.lertora@gmail.com
License: AGPLv3+
Platform: UNKNOWN
Classifier: Programming Language :: Python :: 3
Classifier: License :: OSI Approved :: GNU Affero General Public License v3 or later (AGPLv3+)
Classifier: Operating System :: OS Independent
